yt_dlp_plugins/__init__.py
yt_dlp_plugins/extractor/hentaihaven.py
yt_dlp_plugins/extractor/hentaimama.py
yt_dlp_plugins/extractor/hstream.py
yt_dlp_plugins/extractor/htv.py
yt_dlp_plugins/extractor/ohentai.py
yt_dlp_plugins/extractor/oppaistream.py
hanime_plugin-2026.1.4.dist-info/licenses/LICENSE
hanime_plugin-2026.1.4.dist-info/WHEEL
hanime_plugin-2026.1.4.dist-info/METADATA
hanime_plugin-2026.1.4.dist-info/RECORD
