Metadata-Version: 2.4
Name: hanime-plugin
Version: 2026.1.4
Summary: hanime extractor plugin for yt-dlp
Author-email: Cynthia <cynthia2048@proton.me>
Requires-Python: >=3.9
License-File: LICENSE
